ssb_libtest4/__init__.py
ssb_libtest4/__main__.py
ssb_libtest4/functions.py
ssb_libtest4/py.typed
ssb_libtest4-0.0.1.dist-info/METADATA
ssb_libtest4-0.0.1.dist-info/WHEEL
ssb_libtest4-0.0.1.dist-info/entry_points.txt
ssb_libtest4-0.0.1.dist-info/licenses/LICENSE
ssb_libtest4-0.0.1.dist-info/RECORD
