Metadata-Version: 2.4
Name: ssb-libtest4
Version: 0.0.1
Summary: SSB Libtest4
License-Expression: MIT
License-File: LICENSE
Author: Fredrick Blikeng
Author-email: fbl@ssb.no
Maintainer: Statistics Norway, Microdata Department (380)
Requires-Python: >=3.10,<4.0
Classifier: Development Status :: 3 - Alpha
Classifier: Programming Language :: Python :: 3
Classifier: Programming Language :: Python :: 3.10
Classifier: Programming Language :: Python :: 3.11
Classifier: Programming Language :: Python :: 3.12
Classifier: Programming Language :: Python :: 3.13
Classifier: Programming Language :: Python :: 3.14
Requires-Dist: click (>=8.0.1)
Project-URL: Changelog, https://github.com/statisticsnorway/ssb-libtest4/releases
Project-URL: Documentation, https://statisticsnorway.github.io/ssb-libtest4
Project-URL: Homepage, https://github.com/statisticsnorway/ssb-libtest4
Project-URL: Repository, https://github.com/statisticsnorway/ssb-libtest4
